Workbook

Sheet 总表
A1: 公司 | B1: 年度/口径 | C1: 收入 | D1: 单位 | E1: 收入构成 | F1: 毛利率(不含研发) | G1: 经营利润率 | H1: 净利率 | I1: 成本结构要点 | J1: 信源分级
A2: OpenAI | B2: 2025 | C2: 13.07 | D2: USD B | E2: ChatGPT 订阅+API+企业（未完整拆分） | F2: =成本明细!M2 -> 0.42616679 | G2: =成本明细!N2 -> -1.6006121 | H2: =成本明细!O2 -> -2.9479725 | I2: 研发 $19.18B 为最大成本项（=收入 1.5 倍）；COGS $7.5B 主要为推理算力；全年总成本 $34B；付微软算力费 $10.59B；电力不单列 | J2: P1- 独家获得财务文件·未经审计(Where's Your Ed At)
A3: OpenAI | B3: 2024 | C3: 3.7 | D3: USD B | E3: 同上 | F3: =成本明细!M3 -> 0.28378378 | G3: =成本明细!N3 -> -2.372973 | H3: =成本明细!O3 -> -1.3756757 | I3: 研发 $7.81B；COGS $2.65B | J3: 同上
A4: Anthropic | B4: 2025 年末年化 | C4: 9 | D4: USD B·年化 | E4: 企业/API 占 80-85%；1000+ 客户年付超 $1M | F4: 约 40%（公司投资者口径·报道；2024 约 -94%，2026E≈44%，2028 目标 77%） | G4: — | H4: — | I4: 云基础设施承诺 ~$80B（至 2029·AWS+Google）；2026E 净亏 ~$2B、burn≈收入 33%；2021-25 累计亏损估 $10-15B；2026 run-rate：2月 $14B→4月 $30B→5月 $47B（Series H·估值 $965B） | J4: P1/P2 融资披露+报道·未经审计
A5: xAI（SpaceX 分部） | B5: 2025 | C5: 3.2 | D5: USD B | E5: ⚠ 含 X 广告收入，纯 AI(Grok 订阅/API) 占少数；Grok 117M MAU、仅 1.9M 付费 | F5: —（S-1 未拆毛利） | G5: =成本明细!N5 -> -2 | H5: — | I5: capex $12.7B（Colossus 数据中心）；2026Q1 capex $7.7B（年化 ~$30B）；经营亏损 $6.4B | J5: P0/P1 SpaceX IPO 招股书（S-1）转述
A6: xAI（SpaceX 分部） | B6: 2026 Q1 | C6: 0.818 | D6: USD B | E6: 同上 | F6: — | G6: =成本明细!N6 -> -3.0195599 | H6: — | I6: 单季经营亏损 $2.47B（占 SpaceX 当季收入 17%） | J6: 同上
A7: SpaceX 集团 | B7: 2025 | C7: 16 | D7: USD B | E7: 发射+Starlink（9.2M+ 用户）+xAI | F7: — | G7: — | H7: — | I7: EBITDA $7.5B（margin≈47%）；Starlink EBITDA margin≈63%；2026-02 合并 xAI，合并估值 $1.25T，IPO 目标 $1.5-1.75T | J7: P1 报道
A8: 微软（集团） | B8: FY2026（至 2026-06） | C8: 331.8 | D8: USD B | E8: Azure 年收入首破 $100B（+41%）；AI 业务年化 $37B（+123%）；M365 Copilot 付费席 3000 万+ | F8: —（云分部毛利不单列；Microsoft Cloud 毛利率 FY25 约 69%，FY26 受 AI 基建摊薄·精确值缺） | G8: =成本明细!N8 -> 0.46775166 | H8: — | I8: FY capex $115.9B（Q4 $41B·2/3 为 GPU/CPU 短寿命资产）；FY27Q1 指引 >$50B；商业 RPO $678B（+84%）；折旧未单列 | J8: P0 财报/IR
A9: Alphabet（集团） | B9: FY2025 | C9: 402.8 | D9: USD B | E9: Google Services $350B+Cloud $58.7B+Other Bets | F9: —（集团毛利率约 57-58%·未单列披露口径差异） | G9: — | H9: =成本明细!O9 -> 0.32820258 | I9: capex $91.4B（+74%）；折旧 $21.1B（2024: $15.3B，+38%）；服务器 6 年折旧、约占基建 60%；2026 capex 指引 ~$175-205B；电力含在数据中心成本·不单列 | J9: P0 10-K/8-K
A10: Google Cloud | B10: FY2025 | C10: 58.7 | D10: USD B | E10: GCP（企业 AI 基建+AI 方案）+Workspace；年末年化 >$70B | F10: —（分部不披露毛利） | G10: =成本明细!N10 -> 0.23679727 | H10: — | I10: Q4 单季 $17.7B(+48%)、Q4 经营利润率 30%；全年经营利润为四季加总（2.18+2.83+3.59+5.3） | J10: P0 财报
A11: Amazon（集团） | B11: FY2025 | C11: 716.9 | D11: USD B | E11: 北美 $426.3B+国际 $161.9B+AWS $128.7B | F11: — | G11: =成本明细!N11 -> 0.11159157 | H11: =成本明细!O11 -> 0.10838332 | I11: 2025 capex ~$125B（P1）；2026 计划 ~$200B（P0·绝大部分投 AWS/AI） | J11: P0 财报
A12: AWS | B12: FY2025 | C12: 128.7 | D12: USD B | E12: 云+AI 基建（自研芯片年化 >$10B、三位数增长） | F12: —（分部不披露毛利） | G12: =成本明细!N12 -> 0.35431235 | H12: — | I12: Q4 $35.6B(+24%)、年化 $142B；2025 新增电力容量 3.99GW、2027 底前翻倍——电力唯一有量的公司；经营利润 $45.6B（占集团 57%） | J12: P0 财报
A13: 阿里巴巴（集团） | B13: FY2026（至 2026-03） | C13: 10236.7 | D13: RMB 亿 | E13: 电商+云智能 ¥1,581亿+即时零售等 | F13: — | G13: =成本明细!N13 -> 0.048990397 | H13: =成本明细!O13 -> 0.099765549 | I13: 经调整 EBITA ¥764亿(-56%)；利润大降主因即时零售+AI/云投入；三年 ¥3,800亿 AI+云基建 | J13: P0 财报
A14: 阿里云智能 | B14: FY2026（至 2026-03） | C14: 1581.32 | D14: RMB 亿 | E14: 外部商业化收入破 ¥1,000亿（+40%）；AI 相关占云外部收入 30%·AI ARR >¥358亿·连续 11 季三位数增长 | F14: — | G14: —（FY26 全年云 EBITA 未见干净披露；早期季度约 9-10%） | H14: — | I14: 目标 5 年云收入 $1,000亿、margin 20%；千问衍生模型 18 万+（HuggingFace 第一）；百炼客户 +8 倍 | J14: P0 财报
A15: 智谱（02513.HK） | B15: 2025 | C15: 7.24 | D15: RMB 亿 | E15: 企业级通用大模型 50.4%·开放平台/API 26.3%（+292.6%）·企业级智能体 22.9% | F15: =成本明细!M15 -> 0.41022099 | G15: — | H15: =成本明细!O15 -> -6.5165746 | I15: 研发 ¥31.8亿（=收入 4.4 倍）；capex ¥0.75亿（-83.8%·固定租赁转『租赁+服务采购』）；本地化毛利率 48.8%、云端 18.9%；经调整净亏 ¥31.82亿 | J15: P0 年报/招股书（2026-01-08 上市）
A16: 月之暗面（Kimi） | B16: 2025 | C16: 1.18 | D16: RMB 亿 | E16: API 占 70%+；海外收入 > 国内 | F16: — | G16: — | H16: — | I16: K2 单次训练成本 $460 万（口径：单次 run·非总研发）；现金 >¥100亿；付费 2025-09 才开启；2026-04 ARR >$2亿；估值 $350亿（2026-07）；亏损/毛利全未披露 | J16: P2 报道
A17: DeepSeek | B17: 2025 年化（估） | C17: 约 $2-2.5 亿·年化（估） | D17: USD | E17: API 为主；C 端免费 | F17: — | G17: — | H17: — | I17: 幻方体内补贴、无任何公开财报；『545% 利润率』系理论推理毛利、已证伪；SemiAnalysis 旧估累计投入 ~$1.6B（2025-02·P2）；2026 中年化 ~$400-500M（The Information） | J17: P2 报道/推断

Sheet 成本明细
A1: 公司 | B1: 期间 | C1: 币种单位 | D1: 收入 | E1: 营业成本COGS | F1: 研发R&D | G1: 销售S&M | H1: 管理G&A | I1: 经营利润 | J1: 净利润 | K1: capex(硬件采购) | L1: 折旧 | M1: 毛利率(不含研发) | N1: 经营利润率 | O1: 净利率 | P1: 备注
A2: OpenAI | B2: 2025 | C2: USD B | D2: 13.07 | E2: 7.5 | F2: 19.18 | G2: 5.73 | H2: 1.57 | I2: -20.92 | J2: -38.53 | M2: =IF(OR(ISBLANK(D2),ISBLANK(E2)),"—",1-E2/D2) -> 0.42616679 | N2: =IF(OR(ISBLANK(D2),ISBLANK(I2)),"—",I2/D2) -> -1.6006121 | O2: =IF(OR(ISBLANK(D2),ISBLANK(J2)),"—",J2/D2) -> -2.9479725 | P2: 归属净亏含 $41.55B 改制公允价值一次性；2025 付微软算力费 $10.59B；无自有数据中心（算力全租）。电力不单列
A3: OpenAI | B3: 2024 | C3: USD B | D3: 3.7 | E3: 2.65 | F3: 7.81 | G3: 1.11 | H3: 0.907 | I3: -8.78 | J3: -5.09 | M3: =IF(OR(ISBLANK(D3),ISBLANK(E3)),"—",1-E3/D3) -> 0.28378378 | N3: =IF(OR(ISBLANK(D3),ISBLANK(I3)),"—",I3/D3) -> -2.372973 | O3: =IF(OR(ISBLANK(D3),ISBLANK(J3)),"—",J3/D3) -> -1.3756757
A4: Anthropic | B4: 2025(年化) | C4: USD B·年化 | D4: 9 | M4: =IF(OR(ISBLANK(D4),ISBLANK(E4)),"—",1-E4/D4) -> — | N4: =IF(OR(ISBLANK(D4),ISBLANK(I4)),"—",I4/D4) -> — | O4: =IF(OR(ISBLANK(D4),ISBLANK(J4)),"—",J4/D4) -> — | P4: 年末年化≈$9B（实际确认收入未完整披露，估 $4-5B·P2 推断）；毛利率≈40%（公司投资者口径·2024 约-94%）；云承诺 ~$80B 至2029(AWS+Google)；2026E 净亏 ~$2B
A5: xAI | B5: 2025 | C5: USD B | D5: 3.2 | I5: -6.4 | K5: 12.7 | M5: =IF(OR(ISBLANK(D5),ISBLANK(E5)),"—",1-E5/D5) -> — | N5: =IF(OR(ISBLANK(D5),ISBLANK(I5)),"—",I5/D5) -> -2 | O5: =IF(OR(ISBLANK(D5),ISBLANK(J5)),"—",J5/D5) -> — | P5: 收入含 X 广告，纯 AI(Grok/API) 占少数（Forbes）；capex 主投 Colossus 数据中心
A6: xAI | B6: 2026Q1 | C6: USD B | D6: 0.818 | I6: -2.47 | K6: 7.7 | M6: =IF(OR(ISBLANK(D6),ISBLANK(E6)),"—",1-E6/D6) -> — | N6: =IF(OR(ISBLANK(D6),ISBLANK(I6)),"—",I6/D6) -> -3.0195599 | O6: =IF(OR(ISBLANK(D6),ISBLANK(J6)),"—",J6/D6) -> — | P6: capex 单季年化≈$30B
A7: SpaceX 集团 | B7: 2025 | C7: USD B | D7: 16 | M7: =IF(OR(ISBLANK(D7),ISBLANK(E7)),"—",1-E7/D7) -> — | N7: =IF(OR(ISBLANK(D7),ISBLANK(I7)),"—",I7/D7) -> — | O7: =IF(OR(ISBLANK(D7),ISBLANK(J7)),"—",J7/D7) -> — | P7: EBITDA $7.5B(46.9%)；Starlink EBITDA margin≈63%；合并 xAI 后估值 $1.25T；$20B 过桥贷置换 xAI $16B 债
A8: 微软(集团) | B8: FY2026(至26-06) | C8: USD B | D8: 331.8 | I8: 155.2 | K8: 115.9 | M8: =IF(OR(ISBLANK(D8),ISBLANK(E8)),"—",1-E8/D8) -> — | N8: =IF(OR(ISBLANK(D8),ISBLANK(I8)),"—",I8/D8) -> 0.46775166 | O8: =IF(OR(ISBLANK(D8),ISBLANK(J8)),"—",J8/D8) -> — | P8: Azure 年收入首破 $100B(+41%)；AI 业务年化 $37B(+123%·Q3 披露)；Q4 capex $41B 中 2/3 为 GPU/CPU 短寿命资产；RPO $678B(+84%)；云分部毛利/折旧未单列
A9: Alphabet(集团) | B9: FY2025 | C9: USD B | D9: 402.8 | J9: 132.2 | K9: 91.4 | L9: 21.1 | M9: =IF(OR(ISBLANK(D9),ISBLANK(E9)),"—",1-E9/D9) -> — | N9: =IF(OR(ISBLANK(D9),ISBLANK(I9)),"—",I9/D9) -> — | O9: =IF(OR(ISBLANK(D9),ISBLANK(J9)),"—",J9/D9) -> 0.32820258 | P9: capex +74%(2024: $52.5B)；折旧 2024: $15.3B→2025: $21.1B；服务器 6 年折旧、约占基建 60%；2026 capex 指引 ~$175-205B
A10: Google Cloud | B10: FY2025 | C10: USD B | D10: 58.7 | I10: 13.9 | M10: =IF(OR(ISBLANK(D10),ISBLANK(E10)),"—",1-E10/D10) -> — | N10: =IF(OR(ISBLANK(D10),ISBLANK(I10)),"—",I10/D10) -> 0.23679727 | O10: =IF(OR(ISBLANK(D10),ISBLANK(J10)),"—",J10/D10) -> — | P10: 收入为四季加总(12.26+13.62+15.16+17.66)；Q4 单季 $17.7B(+48%)、Q4 经营利润率 30%；年末年化 >$70B；分部毛利不披露
A11: Amazon(集团) | B11: FY2025 | C11: USD B | D11: 716.9 | I11: 80 | J11: 77.7 | K11: 125 | M11: =IF(OR(ISBLANK(D11),ISBLANK(E11)),"—",1-E11/D11) -> — | N11: =IF(OR(ISBLANK(D11),ISBLANK(I11)),"—",I11/D11) -> 0.11159157 | O11: =IF(OR(ISBLANK(D11),ISBLANK(J11)),"—",J11/D11) -> 0.10838332 | P11: capex ~$125B(P1·电话会口径)；2026 计划 ~$200B(P0·主投 AWS/AI)
A12: AWS | B12: FY2025 | C12: USD B | D12: 128.7 | I12: 45.6 | M12: =IF(OR(ISBLANK(D12),ISBLANK(E12)),"—",1-E12/D12) -> — | N12: =IF(OR(ISBLANK(D12),ISBLANK(I12)),"—",I12/D12) -> 0.35431235 | O12: =IF(OR(ISBLANK(D12),ISBLANK(J12)),"—",J12/D12) -> — | P12: Q4 $35.6B(+24%)、年化 $142B；自研芯片(Graviton+Trainium)年化收入 >$10B、三位数增长；2025 新增电力容量 3.99GW、2027 底前翻倍——电力口径唯一给出量的公司
A13: 阿里巴巴(集团) | B13: FY2026(至26-03) | C13: RMB 亿 | D13: 10236.7 | I13: 501.5 | J13: 1021.27 | M13: =IF(OR(ISBLANK(D13),ISBLANK(E13)),"—",1-E13/D13) -> — | N13: =IF(OR(ISBLANK(D13),ISBLANK(I13)),"—",I13/D13) -> 0.048990397 | O13: =IF(OR(ISBLANK(D13),ISBLANK(J13)),"—",J13/D13) -> 0.099765549 | P13: 经调整 EBITA ¥764.16亿(-56%)；利润大降主因即时零售+AI/云战略投入；三年 ¥3,800亿 AI+云基建计划
A14: 阿里云智能 | B14: FY2026(至26-03) | C14: RMB 亿 | D14: 1581.32 | M14: =IF(OR(ISBLANK(D14),ISBLANK(E14)),"—",1-E14/D14) -> — | N14: =IF(OR(ISBLANK(D14),ISBLANK(I14)),"—",I14/D14) -> — | O14: =IF(OR(ISBLANK(D14),ISBLANK(J14)),"—",J14/D14) -> — | P14: 外部商业化收入破 ¥1,000亿(+40%)；AI 相关 Q4 收入 ¥89.7亿、连续 11 季三位数增长、AI ARR >¥358亿、占云外部收入 30%；FY26 全年云 EBITA 未见干净披露(早期季度约 9-10%)
A15: 智谱(02513.HK) | B15: 2025 | C15: RMB 亿 | D15: 7.24 | E15: 4.27 | F15: 31.8 | J15: -47.18 | K15: 0.747 | M15: =IF(OR(ISBLANK(D15),ISBLANK(E15)),"—",1-E15/D15) -> 0.41022099 | N15: =IF(OR(ISBLANK(D15),ISBLANK(I15)),"—",I15/D15) -> — | O15: =IF(OR(ISBLANK(D15),ISBLANK(J15)),"—",J15/D15) -> -6.5165746 | P15: 经调整净亏 ¥31.82亿(-439%)；研发占收入 439%；本地化部署毛利率 48.8%、云端 18.9%；capex -83.8%(固定租赁转『租赁+服务采购』)；MaaS ARR ¥17亿；2026Q1 API 提价 83%
A16: 月之暗面(Kimi) | B16: 2025 | C16: RMB 亿 | D16: 1.18 | M16: =IF(OR(ISBLANK(D16),ISBLANK(E16)),"—",1-E16/D16) -> — | N16: =IF(OR(ISBLANK(D16),ISBLANK(I16)),"—",I16/D16) -> — | O16: =IF(OR(ISBLANK(D16),ISBLANK(J16)),"—",J16/D16) -> — | P16: 付费 2025-09 才开启；2026-02 K2.5 后 20 天收入超 2025 全年；2026-04 ARR >$2亿；K2 单次训练成本 $460万(口径:单次 run·非总研发)；现金 >¥100亿；亏损/毛利未披露
A17: DeepSeek | B17: 2025(年化估) | C17: USD B | M17: =IF(OR(ISBLANK(D17),ISBLANK(E17)),"—",1-E17/D17) -> — | N17: =IF(OR(ISBLANK(D17),ISBLANK(I17)),"—",I17/D17) -> — | O17: =IF(OR(ISBLANK(D17),ISBLANK(J17)),"—",J17/D17) -> — | P17: 年化收入 ~$200-250M(2025 run-rate·The Information 称 2026 中 ~$400-500M 为两倍)；幻方体内补贴、无任何公开财报；『545% 利润率』系理论推理毛利、已证伪；SemiAnalysis 旧估累计投入 ~$1.6B(2025-02·P2)

Sheet 口径与信源
A1: 类别 | B1: 内容
A2: 信源分级 | B2: P0＝审计财报/招股书/SEC 或 HKEX 文件；P1＝权威财经媒体报道、公司融资披露转述、财报电话会口径；P2＝一般媒体/第三方估计/推断。私企数据全部未经审计。
A3: 口径① 毛利率 | B3: 「毛利率（不含研发）」＝1−营业成本/收入。仅 OpenAI、智谱有干净 COGS 拆分可算；云厂商（微软/谷歌/亚马逊/阿里）分部只披露到经营利润、不披露分部毛利，其经营利润率已含研发与折旧摊薄，与实验室口径不可直接横比——本表对此一律标『—』，不做臆造换算。
A4: 口径② 收入 | B4: 实收与年化（run-rate）严格分列：Anthropic/DeepSeek/阿里 AI 的年化值 ≠ 全年确认收入。Anthropic 2025 实际确认收入未见完整披露（估 $4-5B·P2 推断，表内未填）。
A5: 口径③ 电力 | B5: 电力成本几乎所有公司都不单列，含在数据中心租金/折旧/COGS 内——这本身是行业现状要点。唯一例外：AWS 披露 2025 新增电力容量 3.99GW、2027 底前翻倍（容量非金额）。
A6: 口径④ 硬件与折旧 | B6: 自建派（谷歌/亚马逊/微软/xAI）：capex→折旧进成本，谷歌服务器 6 年折旧；租用派（OpenAI/Anthropic/智谱/Kimi/DeepSeek）：算力以租赁费进 COGS 或研发，无自有大额 capex——两派成本科目结构不同，横比时注意。智谱 2025 把固定租赁转『租赁+服务采购』后 capex 降 84%，是租自混合的第三种形态。
A7: 口径⑤ 币种 | B7: 一律原币（USD B／RMB 亿）不换算，避免引入汇率假设。粗换算参考：表外自乘 7.1-7.2（2026-08 汇率未核，使用时请自行核实）。
A8: 口径⑥ xAI | B8: S-1 中 xAI 分部收入含 X（Twitter）广告，纯 AI 收入占少数（Forbes 2026-06 报道）——把 $3.2B 全当 AI 收入会严重高估。
A9: 口径⑦ OpenAI 净利 | B9: 2025 归属净亏 $38.53B 含 $41.55B 非营利转营利的可转换权益公允价值一次性变动；经营亏损 $20.92B 更能反映经营性烧钱速度。
A10: 缺口声明 | B10: 未见可靠披露即留『—』，宁缺毋假：Anthropic 2025 实收、Kimi 亏损与毛利、DeepSeek 全部成本科目、微软/阿里云分部毛利率、各家电力金额、xAI 毛利率。
A11: 信源·P0 | B11: Amazon Q4/FY2025 财报 ir.aboutamazon.com｜Alphabet Q4/FY2025 8-K（SEC: googexhibit991q42025.htm）+ 10-K｜Microsoft FY26Q4 IR（microsoft.com/en-us/investor）｜阿里巴巴 FY2026 业绩（alibabagroup.com）｜智谱 2025 年报（HKEX 20260331 公告）｜SpaceX/xAI S-1（经 TechCrunch/Morningstar 转述，未见原文逐行核对→P0/P1 之间）
A12: 信源·P1 | B12: Where's Your Ed At 独家：OpenAI 2025 财务文件（wheresyoured.at/exclusive-openai-financials/）｜AWS capex ~$125B（电话会口径）｜Alphabet capex $91.4B/折旧 $21.1B（10-K 转述+fool.com 分析）｜Forbes：xAI 收入含 X 广告｜DCD：Anthropic 云承诺 $80B
... A15: 制作 | B15: CC 2026-08-10 制·web 检索+原文抓取；私企数字请以『未经审计』对待；引用前建议回指上列信源再核一遍。
